<?xml version="1.0" encoding="utf-8"?>
<!DOCTYPE hibernate-mapping PUBLIC "-//Hibernate/Hibernate Mapping DTD 3.0//EN"
"http://hibernate.sourceforge.net/hibernate-mapping-3.0.dtd">
<!-- 
    Mapping file autogenerated by MyEclipse Persistence Tools
-->
<hibernate-mapping>
    <class name="com.mftour.spring.model.Accounts" table="accounts">
        <id name="userId" type="java.lang.String">
            <column name="userId" length="100" not-null="true"/>
            <generator class="native" />
        </id>
        <property name="availableMoney" type="java.math.BigDecimal">
            <column name="availableMoney" length="16" default="0"/>
        </property>
        <property name="availableReward" type="java.math.BigDecimal">
            <column name="availableReward" length="16" default="0"/>
        </property>
        <property name="frozen_money_invest" type="java.math.BigDecimal">
            <column name="frozen_money_invest" length="16" default="0" />
        </property>
        <property name="frozen_money_repay" type="java.math.BigDecimal">
            <column name="frozen_money_repay" length="16" default="0"/>
        </property>
        <property name="frozenMoneyWithdraw" type="java.math.BigDecimal">
            <column name="frozenMoneyWithdraw" length="16" default="0" />
        </property>
        <property name="frozenRewardRay" type="java.math.BigDecimal">
            <column name="frozenRewardRay" length="16" default="0"/>
        </property>
        <property name="usedReward" type="java.math.BigDecimal">
            <column name="usedReward" length="16" default="0"/>
        </property>
        <property name="receivablePrincipal" type="java.math.BigDecimal">
            <column name="receivablePrincipal" length="16" default="0"/>
        </property>
        <property name="receivableInterest" type="java.math.BigDecimal">
            <column name="receivableInterest" length="16" default="0"/>
        </property>
        <property name="accumulateRecharge" type="java.math.BigDecimal">
            <column name="accumulateRecharge" length="16" default="0"/>
        </property>
        <property name="accumulateRechargeCount" type="java.lang.Integer">
            <column name="accumulateRechargeCount" length="11" default="0"/>
        </property>

        <property name="accumulatePrincipal" type="java.math.BigDecimal">
            <column name="accumulatePrincipal" length="16" default="0"/>
        </property>
        <property name="accumulate_money_invest" type="java.math.BigDecimal">
            <column name="accumulate_money_invest" length="16" default="0"/>
        </property>
        <property name="accumulateInterest" type="java.math.BigDecimal">
            <column name="accumulateInterest" length="16" default="0"/>
        </property>
         <property name="accumulateInvest_count" type="java.lang.Integer">
            <column name="accumulateInvest_count" length="11" default="0"/>
        </property>
        <property name="accumulateFreeWithdraw" type="java.math.BigDecimal">
            <column name="accumulateFreeWithdraw" length="16" default="0"/>
        </property>
        <property name="accumulateWithdraw" type="java.math.BigDecimal">
            <column name="accumulateWithdraw" length="16" default="0" />
        </property>
         <property name="accumulateWithdrawCount" type="java.lang.Integer">
            <column name="accumulateWithdrawCount" length="11" default="0"/>
        </property>
        <property name="balanceAvailable" type="java.math.BigDecimal">
            <column name="balanceAvailable" length="16" default="0"/>
        </property>
        <property name="balanceTotal" type="java.math.BigDecimal">
            <column name="balanceTotal" length="16" default="0"/>
        </property>
        <property name="yeepayBindcardCardno" type="java.lang.String">
            <column name="yeepayBindcardCardno" length="16" />
        </property>
        <property name="yeepayBindcardBank" type="java.lang.String">
            <column name="yeepayBindcardBank" length="16" />
        </property>
        <property name="yeepayBindcardIsok" type="java.lang.Boolean">
            <column name="yeepayBindcardIsok" length="1" default="0"/>
        </property>
        <property name="accumulateLender" type="java.math.BigDecimal">
            <column name="accumulateLender" length="16" default="0"/>
        </property>
        <property name="accumulateRepay" type="java.math.BigDecimal">
            <column name="accumulateRepay" length="16" default="0"/>
        </property>
        <property name="accumulateRepayCount" type="java.math.BigDecimal">
            <column name="accumulateRepayCount" length="16" default="0"/>
        </property>
        <property name="yeepayAccumulateRepay" type="java.math.BigDecimal">
            <column name="yeepayAccumulateRepay" length="16" default="0"/>
        </property>
        <property name="otherAccumulateRepay" type="java.math.BigDecimal">
            <column name="otherAccumulateRepay" length="16" default="0"/>
        </property>
        <property name="accumuateLenderInterest" type="java.math.BigDecimal">
            <column name="accumuateLenderInterest" length="16" default="0"/>
        </property>
       
    </class>
</hibernate-mapping>
